{
  "GuideData": {


    "AdsController": [
      {
        "NetworkAds": "mix",
        "AdMobId": "",

        "BannerAdmob": "",
        "InterstitialAdmob": "",
        "NativeAdmob": "",

        "BannerFacebook": "1047688085699214_1047689332365756",
        "InterstitialFacebook": "1047688085699214_1047688709032485",
        "NativeFacebook": "1047688085699214_1047926895675333"

      }
    ],

  
  "items": [
      
      {
        "title": "",
        "image": "https://guides.gamepressure.com/hello_neighbor/gfx/word/613470577.jpg"
      },
       {
        "title": "",
        "image": "https://guides.gamepressure.com/hello_neighbor/gfx/word/613470593.jpg"
      },
        {
        "title": "",
        "image": "https://guides.gamepressure.com/hello_neighbor/gfx/word/613470608.jpg"
      },
      {
        "title": "",
        "image": "https://guides.gamepressure.com/hello_neighbor/gfx/word/613470624.jpg"
      },
      {
        "title": "",
        "image": "https://guides.gamepressure.com/hello_neighbor/gfx/word/613470640.jpg"
      },
       {
        "title": "",
        "image": "https://guides.gamepressure.com/hello_neighbor/gfx/word/613470655.jpg"
         },
       {
        "title": "",
        "image": "https://guides.gamepressure.com/hello_neighbor/gfx/word/613470671.jpg"
         },
       {
        "title": "",
        "image": "https://guides.gamepressure.com/hello_neighbor/gfx/word/613470686.jpg"
         },
       {
        "title": "",
        "image": "https://guides.gamepressure.com/hello_neighbor/gfx/word/613470702.jpg"
         },
       {
        "title": "",
        "image": "https://guides.gamepressure.com/hello_neighbor/gfx/word/613470718.jpg"
         },
       {
        "title": "",
        "image": "https://guides.gamepressure.com/hello_neighbor/gfx/word/613470733.jpg"
         },
       {
        "title": "",
        "image": "https://guides.gamepressure.com/hello_neighbor/gfx/word/613470749.jpg"
      }
    ],

    "content1": [
      {
        "ordered": "image_text",
        "color": "#FFFFFF","style": "blood",
        "gravity": "left",
        "left": "10",
        "text_size": "25",
        "isLink": "false","link_title": "","setLink": "",
        "image_link": "",
        "text": "Intro",
        "isNative": "true"
      },
      {
        "ordered": "image_text",
        "color": "#FFFFFF","style": "blood",
        "gravity": "left",
        "left": "5",
        "text_size": "20",
        "isLink": "false","link_title": "","setLink": "",
        "image_link": "https://guides.gamepressure.com/hello_neighbor/gfx/word/613470593.jpg",
        "text": " Some overlap exists between Hello Neighbor Acts II and III. If you haven't yet finished the in-between segment taking place in a different time, walk into your house for a cutscene, then grab the green key out of the car trunk to access the neighbor's house and pick up the phone. With that out of the way, it's time to get started back on the regular gameplay.

First, grab any small, throwable item (such as the VHS tape in your house) and two boxes. There are again boxes in the closet of your house, or you can find some outside in the neighbor's yard.",
        "isNative": "true"
      }
    ],
    
    "content2": [
      {
        "ordered": "image_text",
        "color": "#FFFFFF","style": "blood",
        "gravity": "left",
        "left": "10",
        "text_size": "25",
        "isLink": "false","link_title": "","setLink": "",
        "image_link": "",
        "text": " Tips ",
        "isNative": "true"
      },
      {
        "ordered": "image_text",
        "color": "#FFFFFF","style": "blood",
        "gravity": "left",
        "left": "5",
        "text_size": "20",
        "isLink": "false","link_title": "Download new sport streaming app ","setLink": "",
        "image_link": "https://guides.gamepressure.com/hello_neighbor/gfx/word/613470608.jpg",
        "text": " It’s important to remember that a community where people feel uncomfortable or threatened is not a productive one.",
        "isNative": "true"
      }
    ],
    
    "content3": [
      {
        "ordered": "image_text",
        "color": "#FFFFFF","style": "blood",
        "gravity": "left",
        "left": "10",
        "text_size": "25",
        "isLink": "false","link_title": "","setLink": "",
        "image_link": "https://guides.gamepressure.com/hello_neighbor/gfx/word/613470624.jpg",
        "text": "",
        "isNative": "true"
      },
      {
        "ordered": "image_text",
        "color": "#FFFFFF","style": "blood",
        "gravity": "left",
        "left": "5",
        "text_size": "20",
        "isLink": "false","link_title": "click to enter ","setLink": "",
        "image_link": "https://guides.gamepressure.com/hello_neighbor/gfx/word/613470640.jpg",
        "text": " Roblox games are social, multiplayer experiences. In fact, Roblox could be your child’s first experience with digital socializing. ",
        "isNative": "true"
      }
    ],
    "content4": [
      {
        "ordered": "image_text",
        "color": "#FFFFFF","style": "blood",
        "gravity": "left",
        "left": "10",
        "text_size": "25",
        "isLink": "false","link_title": "","setLink": "",
        "image_link": "",
        "text": "The Fall",
        "isNative": "true"
      },
      {
        "ordered": "image_text",
        "color": "#FFFFFF","style": "blood",
        "gravity": "left",
        "left": "5",
        "text_size": "20",
        "isLink": "false","link_title": "click to watch","setLink": "",
        "image_link": "https://guides.gamepressure.com/hello_neighbor/gfx/word/613470655.jpg",
        "text": " Players can comment and converse with other players inside a game and also chat with their friends on Roblox.",
        "isNative": "true"
      }
    ],
    "content5": [
      {
        "ordered": "image_text",
        "color": "#FFFFFF","style": "blood",
        "gravity": "left",
        "left": "10",
        "text_size": "25",
        "isLink": "false","link_title": "","setLink": "",
        "image_link": "",
        "text": "The Fall",
        "isNative": "true"
      },
      {
        "ordered": "image_text",
        "color": "#FFFFFF","style": "blood",
        "gravity": "left",
        "left": "5",
        "text_size": "20",
        "isLink": "false","link_title": "click here","setLink": "",
        "image_link": "https://guides.gamepressure.com/hello_neighbor/gfx/word/613470671.jpg",
        "text": " Launched in 2006, Roblox’s popularity among gamers 8-years-old and up has exploded, and it is now one of the top online entertainment platforms for kids and teens, according to comScore.",
        "isNative": "true"
      }
    ],
    "content6": [
      {
        "ordered": "image_text",
        "color": "#FFFFFF","style": "blood",
        "gravity": "left",
        "left": "10",
        "text_size": "25",
        "isLink": "false","link_title": "","setLink": "",
        "image_link": "https://guides.gamepressure.com/hello_neighbor/gfx/word/613470686.jpg",
        "text": "Cain and Abel",
        "isNative": "true"
      },
      {
        "ordered": "image_text",
        "color": "#FFFFFF","style": "blood",
        "gravity": "left",
        "left": "5",
        "text_size": "20",
        "isLink": "false","link_title": "click to watch","setLink": "",
        "image_link": "https://guides.gamepressure.com/hello_neighbor/gfx/word/613470702.jpg",
        "text": " It’s a platform that allows anyone to create their own online games by using its game design tool known as Roblox Studio.",
        "isNative": "true"
      }
    ],
    "content7": [
      {
        "ordered": "image_text",
        "color": "#FFFFFF","style": "blood",
        "gravity": "left",
        "left": "10",
        "text_size": "25",
        "isLink": "false","link_title": "","setLink": "",
        "image_link": "https://guides.gamepressure.com/hello_neighbor/gfx/word/613470718.jpg",
        "text": "Cain and Abel",
        "isNative": "true"
      },
      {
        "ordered": "image_text",
        "color": "#FFFFFF","style": "blood",
        "gravity": "left",
        "left": "5",
        "text_size": "20",
        "isLink": "false","link_title": "click to watch ","setLink": "",
        "image_link": "https://guides.gamepressure.com/hello_neighbor/gfx/word/613470733.jpg",
        "text": " It’s a platform that allows anyone to create their own online games by using its game design tool known as Roblox Studio.",
        "isNative": "true"
      }
    ],
"content8": [
      {
        "ordered": "image_text",
        "color": "#FFFFFF","style": "blood",
        "gravity": "left",
        "left": "10",
        "text_size": "25",
        "isLink": "false","link_title": "","setLink": "",
        "image_link": "https://guides.gamepressure.com/hello_neighbor/gfx/word/613470764.jpg",
        "text": "From Adam to Noah",
        "isNative": "true"
      },
      {
        "ordered": "image_text",
        "color": "#FFFFFF","style": "blood",
        "gravity": "left",
        "left": "5",
        "text_size": "20",
        "isLink": "false","link_title": "click to watch ","setLink": "",
        "image_link": "https://guides.gamepressure.com/hello_neighbor/gfx/word/613470780.jpg",
        "text": " It’s a platform that allows anyone to create their own online games by using its game design tool known as Roblox Studio.",
        "isNative": "true"
      }
    ],
     "content9": [
      {
        "ordered": "image_text",
        "color": "#FFFFFF","style": "blood",
        "gravity": "left",
        "left": "10",
        "text_size": "25",
        "isLink": "false","link_title": "","setLink": "",
        "image_link": "https://guides.gamepressure.com/hello_neighbor/gfx/word/613470796.jpg",
        "text": "From Adam to Noah",
        "isNative": "true"
      },
      {
        "ordered": "image_text",
        "color": "#FFFFFF","style": "blood",
        "gravity": "left",
        "left": "5",
        "text_size": "20",
        "isLink": "false","link_title": "click to watch","setLink": "",
        "image_link": "https://guides.gamepressure.com/hello_neighbor/gfx/word/613470811.jpg",
        "text": " It’s a platform that allows anyone to create their own online games by using its game design tool known as Roblox Studio.",
        "isNative": "true"
      }
    ],
    "content10": [
      {
        "ordered": "image_text",
        "color": "#FFFFFF","style": "blood",
        "gravity": "left",
        "left": "10",
        "text_size": "25",
        "isLink": "false","link_title": "","setLink": "",
        "image_link": "https://guides.gamepressure.com/hello_neighbor/gfx/word/613470827.jpg",
        "text": "Wickedness in the World",
        "isNative": "true"
      },
      {
        "ordered": "image_text",
        "color": "#FFFFFF","style": "blood",
        "gravity": "left",
        "left": "5",
        "text_size": "20",
        "isLink": "false","link_title": "click to watch","setLink": "",
        "image_link": "https://guides.gamepressure.com/hello_neighbor/gfx/word/613470842.jpg",
        "text": " It’s a platform that allows anyone to create their own online games by using its game design tool known as Roblox Studio.",
        "isNative": "true"
      }
    ],
    "content11": [
      {
        "ordered": "image_text",
        "color": "#FFFFFF","style": "blood",
        "gravity": "left",
        "left": "10",
        "text_size": "25",
        "isLink": "false","link_title": "","setLink": "",
        "image_link": "https://guides.gamepressure.com/hello_neighbor/gfx/word/613470858.jpg",
        "text": "Wickedness in the World ",
        "isNative": "true"
      },
      {
        "ordered": "image_text",
        "color": "#FFFFFF","style": "blood",
        "gravity": "left",
        "left": "5",
        "text_size": "20",
        "isLink": "false","link_title": "click to watch","setLink": "",
        "image_link": "https://guides.gamepressure.com/hello_neighbor/gfx/word/613470874.jpg",
        "text": " It’s a platform that allows anyone to create their own online games by using its game design tool known as Roblox Studio.",
        "isNative": "true"
      }
    ],
    "content12": [
      {
        "ordered": "image_text",
        "color": "#FFFFFF","style": "blood",
        "gravity": "left",
        "left": "10",
        "text_size": "25",
        "isLink": "false","link_title": "","setLink": "",
        "image_link": "https://guides.gamepressure.com/hello_neighbor/gfx/word/613470889.jpg",
        "text": "outro",
        "isNative": "true"
      },
      {
        "ordered": "image_text",
        "color": "#FFFFFF","style": "blood",
        "gravity": "left",
        "left": "5",
        "text_size": "20",
        "isLink": "false","link_title": "click to watch ","setLink": "",
        "image_link": "https://guides.gamepressure.com/hello_neighbor/gfx/word/613470920.jpg",
        "text": " It’s a platform that allows anyone to create their own online games by using its game design tool known as Roblox Studio.",
        "isNative": "true"
      }
    ]
  }
}
